similar/__init__.py
similar.py-1.0.dist-info/LICENSE.txt
similar.py-1.0.dist-info/METADATA
similar.py-1.0.dist-info/WHEEL
similar.py-1.0.dist-info/top_level.txt
similar.py-1.0.dist-info/RECORD
