Metadata-Version: 2.1
Name: similar.py
Version: 1.0
Summary: Find similar text easily
Home-page: https://www.github.com/toxicrecker/similar.py
Author: toxicrecker
License: UNKNOWN
Platform: UNKNOWN
Classifier: Programming Language :: Python :: 3
Classifier: License :: OSI Approved :: MIT License
Classifier: Operating System :: OS Independent
Requires-Python: >= 3.6
